odoo8_addon_account_move_line_payable_receivable_filter-8.0.1.0.0.99.dev4-py2.7-nspkg.pth
odoo8_addon_account_move_line_payable_receivable_filter-8.0.1.0.0.99.dev4.dist-info/DESCRIPTION.rst
odoo8_addon_account_move_line_payable_receivable_filter-8.0.1.0.0.99.dev4.dist-info/METADATA
odoo8_addon_account_move_line_payable_receivable_filter-8.0.1.0.0.99.dev4.dist-info/RECORD
odoo8_addon_account_move_line_payable_receivable_filter-8.0.1.0.0.99.dev4.dist-info/WHEEL
odoo8_addon_account_move_line_payable_receivable_filter-8.0.1.0.0.99.dev4.dist-info/metadata.json
odoo8_addon_account_move_line_payable_receivable_filter-8.0.1.0.0.99.dev4.dist-info/namespace_packages.txt
odoo8_addon_account_move_line_payable_receivable_filter-8.0.1.0.0.99.dev4.dist-info/top_level.txt
odoo_addons/account_move_line_payable_receivable_filter/README.rst
odoo_addons/account_move_line_payable_receivable_filter/__init__.py
odoo_addons/account_move_line_payable_receivable_filter/__openerp__.py
odoo_addons/account_move_line_payable_receivable_filter/i18n/account_move_line_payable_receivable_filter.pot
odoo_addons/account_move_line_payable_receivable_filter/i18n/de.po
odoo_addons/account_move_line_payable_receivable_filter/i18n/es.po
odoo_addons/account_move_line_payable_receivable_filter/i18n/fr.po
odoo_addons/account_move_line_payable_receivable_filter/i18n/fr_BE.po
odoo_addons/account_move_line_payable_receivable_filter/i18n/sl.po
odoo_addons/account_move_line_payable_receivable_filter/static/description/icon.png
odoo_addons/account_move_line_payable_receivable_filter/views/account_move_line_view.xml
